metpyx/__init__.py
metpyx/data.py
metpyx/qualities.py
metpyx/quantities.py
metpyx-1.0.0.dist-info/METADATA
metpyx-1.0.0.dist-info/WHEEL
metpyx-1.0.0.dist-info/licenses/LICENSE
metpyx-1.0.0.dist-info/RECORD
