Metadata-Version: 2.3
Name: metpyx
Version: 1.0.0
Summary: A collection of tools for x-ray metrology
Project-URL: Repository, https://github.com/lmri-met/metpyx
Project-URL: Documentation, https://github.com/lmri-met/metpyx#readme
Project-URL: Issues, https://github.com/lmri-met/metpyx/issues
Author-email: Xandra Campo <xandra.campo@ciemat.es>
Maintainer-email: Xandra Campo <xandra.campo@ciemat.es>
License:                     GNU GENERAL PUBLIC LICENSE
License-File: LICENSE
Keywords: ionizing radiation,metrology,x-rays
Classifier: Development Status :: 4 - Beta
Classifier: Intended Audience :: Science/Research
Classifier: License :: OSI Approved :: GNU General Public License v3 (GPLv3)
Classifier: Operating System :: OS Independent
Classifier: Programming Language :: Python
Classifier: Programming Language :: Python :: 3
Classifier: Programming Language :: Python :: 3.8
Classifier: Programming Language :: Python :: 3.9
Classifier: Programming Language :: Python :: 3.10
Classifier: Programming Language :: Python :: 3.11
Classifier: Programming Language :: Python :: 3.12
Classifier: Programming Language :: Python :: Implementation :: CPython
Classifier: Topic :: Scientific/Engineering :: Physics
Requires-Python: >=3.8
